Workbook

Sheet Lecture
A1: Diplo — modèle de rentabilité
A3: À quoi sert ce classeur
B4: Il répond à trois questions : l'activité peut-elle être rentable, à partir de combien d'abonnés, et quels leviers actionner.
B5: Tout est en formules. Change une hypothèse, tout le modèle se recalcule.
A7: Code couleur
B8: Bleu sur fond jaune = hypothèse que tu peux modifier. C'est le seul type de cellule à éditer.
B9: Noir = calcul. Vert = renvoi vers un autre onglet. N'y touche pas.
A11: Les onglets
A12: Hypotheses | B12: Toutes les entrées du modèle, avec leur source. Commence par vérifier celles marquées À CONFIRMER.
A13: Couts | B13: Coût variable unitaire de chaque génération IA, puis coût mensuel par profil d'utilisateur.
A14: Rentabilite | B14: Marge sur coût variable par abonné et seuil de rentabilité. C'est l'onglet qui donne le verdict.
A15: Compte_resultat | B15: Compte de résultat prévisionnel sur 12 mois.
A16: Scenarios | B16: Trois configurations comparées : actuelle, optimisée, agressive.
A18: Régime retenu
B19: Micro-entreprise, BIC prestations de services. La vente d'abonnements à un logiciel en ligne est une activité
B20: commerciale standardisée, pas une prestation intellectuelle sur mesure : c'est du BIC, pas du BNC.
B21: Cet arbitrage te fait économiser 4,4 points de cotisations (21,2 % au lieu de 25,6 %).
A23: Ce que le modèle ne couvre pas
B24: Ton temps de travail n'est pas valorisé. Le résultat affiché rémunère donc ton travail avant tout.
B25: Pas de budget publicitaire : tu pars en organique. Ajoute-le en charge fixe si tu en mets.
B26: Pas d'impôt sur le revenu hors versement libératoire, ni de CFE en année 1 (exonérée).

Sheet Hypotheses
A1: Hypothèses
A2: Cellules bleues sur fond jaune : à toi de les ajuster. Sources datées de septembre 2026.
A4: A. OFFRE ET PRIX
A5: Prix abonnement Pro | B5: 4.99 | C5: € / mois | D5: Prix actuel de l'app
A6: Prix abonnement Max | B6: 8.99 | C6: € / mois | D6: Prix actuel de l'app
A7: Part des abonnés en Pro | B7: 0.7 | C7: % des payants | D7: Hypothèse — À CONFIRMER
A8: Part des abonnés en Max | B8: =1-B7 -> 0.3
A9: Revenu moyen par abonné (ARPU) | B9: =B5*B7+B6*B8 -> 6.19
A11: B. STATUT : MICRO-ENTREPRISE, BIC PRESTATIONS DE SERVICES
A12: Cotisations sociales BIC prestations de services | B12: 0.212 | C12: % du CA encaissé | D12: URSSAF 2026 — compta-online
A13: Contribution formation professionnelle | B13: 0.001 | C13: % du CA | D13: CFP commerçant, s'ajoute aux cotisations
A14: Versement libératoire IR (BIC services) | B14: 0.017 | C14: % du CA | D14: 1,7 % — wisestart 2026
A15: Option versement libératoire (1 = oui, 0 = non) | B15: 1 | C15: 0 ou 1 | D15: Éligible si RFR 2024 < 29 315 € / part
A16: Taux de prélèvement total sur le CA | B16: =B12+B13+B15*B14 -> 0.23
A17: Abattement forfaitaire micro-BIC services (information) | B17: 0.5 | D17: Sert si tu n'optes pas pour le versement libératoire
A18: Seuil de franchise en base de TVA (services) | B18: 37500 | C18: € / an | D18: Réforme 25 000 € abandonnée, loi 2025-1044
A19: Seuil majoré de TVA (tolérance) | B19: 41250 | C19: € / an | D19: Au-delà : TVA immédiate
A20: Plafond du régime micro (services) | B20: 83600 | C20: € / an | D20: Seuil 2026
A22: C. ENCAISSEMENT DES PAIEMENTS
A23: Commission Stripe (carte européenne) | B23: 0.015 | C23: % par transaction | D23: Stripe France 2026
A24: Frais fixe Stripe par transaction | B24: 0.25 | C24: € par transaction | D24: Stripe France 2026
A26: D. COÛT DE L'IA (Claude Haiku 4.5)
A27: Prix des tokens en entrée | B27: 1 | C27: $ / million de tokens | D27: Tarif Anthropic 2026
A28: Prix des tokens en sortie | B28: 5 | C28: $ / million de tokens | D28: Tarif Anthropic 2026
A29: Taux de change | B29: 0.92 | C29: € pour 1 $ | D29: À CONFIRMER selon le cours du jour
A31: E. ACQUISITION, CONVERSION, RÉTENTION
A32: Taux de conversion gratuit vers payant | B32: 0.021 | C32: % | D32: Médiane freemium 2026 — RevenueCat
A33: Churn mensuel des abonnés | B33: 0.1 | C33: % / mois | D33: Déduit de ~72 % d'annulations en année 1
A34: Nouveaux inscrits gratuits au mois 1 | B34: 300 | C34: inscrits | D34: Hypothèse de lancement — À CONFIRMER
A35: Croissance mensuelle des inscriptions | B35: 0.2 | C35: % / mois | D35: Hypothèse organique — À CONFIRMER
A36: Nombre de gratuits à porter pour 1 payant | B36: =IF(B32<=0,0,1/B32-1) -> 46.619048 | D36: C'est le cœur du problème : chaque payant en finance ce nombre-là
A38: F. CHARGES FIXES MENSUELLES
A39: Supabase Pro | B39: 25 | C39: $ / mois | D39: Supabase 2026 — nécessaire au-delà du gratuit
A40: Lovable Pro | B40: 25 | C40: $ / mois | D40: Lovable 2026
A41: Nom de domaine | B41: 1.5 | C41: € / mois | D41: ~18 €/an
A42: CFE mensualisée | B42: 0 | C42: € / mois | D42: Exonérée l'année de création
A43: Autres (pub, outils) | B43: 0 | C43: € / mois | D43: Organique : 0 €
A44: Total des charges fixes | B44: =(B39+B40)*B29+B41+B42+B43 -> 47.5

Sheet Couts
A1: Coût variable de l'IA
A2: Les volumes de tokens sont des estimations tirées du code des fonctions serveur. Ajuste-les si tu mesures mieux.
A4: 1. COÛT UNITAIRE D'UNE GÉNÉRATION
A5: Action | B5: Tokens en entrée | C5: Tokens en sortie | D5: Coût unitaire (€)
A6: Fiche IA (2 morceaux) | B6: 4600 | C6: 7500 | D6: =(B6/1000000*Hypotheses!$B$27+C6/1000000*Hypotheses!$B$28)*Hypotheses!$B$29 -> 0.038732
A7: Quizz IA | B7: 8000 | C7: 3000 | D7: =(B7/1000000*Hypotheses!$B$27+C7/1000000*Hypotheses!$B$28)*Hypotheses!$B$29 -> 0.02116
A8: Message au coach | B8: 2000 | C8: 500 | D8: =(B8/1000000*Hypotheses!$B$27+C8/1000000*Hypotheses!$B$28)*Hypotheses!$B$29 -> 0.00414
A9: Planning IA | B9: 1500 | C9: 600 | D9: =(B9/1000000*Hypotheses!$B$27+C9/1000000*Hypotheses!$B$28)*Hypotheses!$B$29 -> 0.00414
A10: OCR d'une image | B10: 1600 | C10: 800 | D10: =(B10/1000000*Hypotheses!$B$27+C10/1000000*Hypotheses!$B$28)*Hypotheses!$B$29 -> 0.005152
A12: 2. QUOTAS HEBDOMADAIRES PAR PLAN (tels que codés dans l'app)
A13: Action | B13: Gratuit | C13: Pro | D13: Max
A14: Fiche IA | B14: 1 | C14: 3 | D14: 7
A15: Quizz IA | B15: 7 | C15: 35 | D15: 70
A16: Message au coach | B16: 5 | C16: 46 | D16: 115
A17: Planning IA | B17: 1 | C17: 2 | D17: 8
A18: OCR d'une image | B18: 12 | C18: 60 | D18: 150
A20: 3. COÛT IA MENSUEL PAR UTILISATEUR
A21: Semaines par mois | B21: 4.33 | C21: semaines | D21: 52 / 12
A22: Taux d'utilisation du quota — Gratuit | B22: 0.2 | C22: % du quota | D22: Hypothèse — À CONFIRMER
A23: Taux d'utilisation du quota — Pro | B23: 0.5 | C23: % du quota | D23: Hypothèse — À CONFIRMER
A24: Taux d'utilisation du quota — Max | B24: 0.45 | C24: % du quota | D24: Hypothèse — À CONFIRMER
A26: Profil | B26: Coût si quota saturé | C26: Coût au taux retenu
A27: Utilisateur gratuit | B27: =SUMPRODUCT($D$6:$D$10,B14:B18)*$B$21 -> 1.1843243 | C27: =B27*$B$22 -> 0.23686486
A28: Abonné Pro | B28: =SUMPRODUCT($D$6:$D$10,C14:C18)*$B$21 -> 5.9088739 | C28: =B28*$B$23 -> 2.9544369
A29: Abonné Max | B29: =SUMPRODUCT($D$6:$D$10,D14:D18)*$B$21 -> 13.13871 | C29: =B29*$B$24 -> 5.9124193
A31: Lecture : un abonné Pro qui saturerait tous ses quotas coûterait la valeur de la colonne B en IA.
A32: À comparer à son abonnement de 4,99 €. Si B est au-dessus, le plan est déficitaire à pleine charge.

Sheet Rentabilite
A1: Marge sur coût variable et seuil de rentabilité
A2: Méthode : on isole ce que rapporte un abonné une fois payés tous les coûts qui varient avec lui.
A4: 1. DÉCOMPOSITION D'UN ABONNÉ MOYEN (par mois)
A5: Chiffre d'affaires encaissé (ARPU) | B5: =Hypotheses!B9 -> 6.19 | C5: Prix moyen pondéré Pro / Max
A6: Commission Stripe | B6: =-(Hypotheses!B9*Hypotheses!B23+Hypotheses!B24) -> -0.34285 | C6: 1,5 % + 0,25 € par prélèvement
A7: Cotisations sociales et versement libératoire | B7: =-Hypotheses!B9*Hypotheses!B16 -> -1.4237 | C7: Assis sur le CA encaissé, sans déduction de charges
A8: Coût IA de l'abonné lui-même | B8: =-(Hypotheses!B7*Couts!C28+Hypotheses!B8*Couts!C29) -> -3.8418316 | C8: Sa propre consommation
A9: Coût IA des gratuits qu'il finance | B9: =-Hypotheses!B36*Couts!C27 -> -11.042414 | C9: Chaque payant porte les gratuits non convertis
A10: MARGE SUR COÛT VARIABLE PAR ABONNÉ | B10: =SUM(B5:B9) -> -10.460796
A11: Taux de marge sur coût variable | B11: =IF(B5=0,0,B10/B5) -> -1.6899508
A13: 2. SEUIL DE RENTABILITÉ
A14: Charges fixes mensuelles | B14: =Hypotheses!B44 -> 47.5
A15: Seuil de rentabilité (nombre d'abonnés payants) | B15: =IF(B10<=0,"Jamais atteint",B14/B10) -> Jamais atteint
A16: Chiffre d'affaires mensuel au seuil | B16: =IF(B10<=0,"Jamais atteint",B15*B5) -> Jamais atteint
A17: Inscrits gratuits nécessaires pour y arriver | B17: =IF(B10<=0,"Jamais atteint",B15/Hypotheses!B32) -> Jamais atteint
A18: Durée de vie moyenne d'un abonné (mois) | B18: =IF(Hypotheses!B33<=0,0,1/Hypotheses!B33) -> 10
A19: Valeur vie d'un abonné (LTV, en marge) | B19: =B10*B18 -> -104.60796
A21: Diagnostic | B21: =IF(B10<=0,"MODÈLE DÉFICITAIRE : chaque nouvel abonné creuse la perte. Le seuil de rentabilité n'existe pas.",IF(B10<1,"MARGE TRÈS FAIBLE : il faudrait "&TEXT(B15,"# ##0")&" abonnés pour couvrir les charges fixes.","MODÈLE VIABLE : "&TEXT(B15,"# ##0")&" abonnés suffisent à couvrir les charges fixes.")) -> MODÈLE DÉFICITAIRE : chaque nouvel abonné creuse la perte. Le seuil de rentabilité n'existe pas.
A24: 3. LE POINT CRITIQUE : LE COÛT DU GRATUIT
A25: Coût IA mensuel d'un utilisateur gratuit | B25: =Couts!C27 -> 0.23686486
A26: Gratuits portés par abonné payant | B26: =Hypotheses!B36 -> 46.619048
A27: Coût total du gratuit rapporté à un payant | B27: =B25*B26 -> 11.042414
A28: Part du CA d'un abonné absorbée par les gratuits | B28: =IF(B5=0,0,B27/B5) -> 1.7839118
A30: Coût gratuit maximal admissible pour rester à l'équilibre | B30: =IF(B26=0,0,(B5+B6+B7+B8)/B26) -> 0.012475981 | C30: Au-delà de ce coût par gratuit, l'activité perd de l'argent

Sheet Compte_resultat
A1: Compte de résultat prévisionnel sur 12 mois
A2: Hypothèse : les abonnés se cumulent, diminués du churn mensuel.
A4: Poste | B4: M1 | C4: M2 | D4: M3 | E4: M4 | F4: M5 | G4: M6 | H4: M7 | I4: M8 | J4: M9 | K4: M10 | L4: M11 | M4: M12 | N4: Total année
A5: Nouveaux inscrits gratuits | B5: =Hypotheses!$B$34 -> 300 | C5: =B5*(1+Hypotheses!$B$35) -> 360 | D5: =C5*(1+Hypotheses!$B$35) -> 432 | E5: =D5*(1+Hypotheses!$B$35) -> 518.4 | F5: =E5*(1+Hypotheses!$B$35) -> 622.08 | G5: =F5*(1+Hypotheses!$B$35) -> 746.496 | H5: =G5*(1+Hypotheses!$B$35) -> 895.7952 | I5: =H5*(1+Hypotheses!$B$35) -> 1074.9542 | J5: =I5*(1+Hypotheses!$B$35) -> 1289.9451 | ... M5: =L5*(1+Hypotheses!$B$35) -> 2229.0251 | N5: =SUM(B5:M5) -> 11874.151
A6: Base d'utilisateurs gratuits | B6: =B5*(1-Hypotheses!$B$32) -> 293.7 | C6: =B6+C5*(1-Hypotheses!$B$32) -> 646.14 | D6: =C6+D5*(1-Hypotheses!$B$32) -> 1069.068 | E6: =D6+E5*(1-Hypotheses!$B$32) -> 1576.5816 | F6: =E6+F5*(1-Hypotheses!$B$32) -> 2185.5979 | G6: =F6+G5*(1-Hypotheses!$B$32) -> 2916.4175 | H6: =G6+H5*(1-Hypotheses!$B$32) -> 3793.401 | I6: =H6+I5*(1-Hypotheses!$B$32) -> 4845.7812 | J6: =I6+J5*(1-Hypotheses!$B$32) -> 6108.6374 | ... M6: =L6+M5*(1-Hypotheses!$B$32) -> 11624.794
A7: Nouveaux abonnés | B7: =B5*Hypotheses!$B$32 -> 6.3 | C7: =C5*Hypotheses!$B$32 -> 7.56 | D7: =D5*Hypotheses!$B$32 -> 9.072 | E7: =E5*Hypotheses!$B$32 -> 10.8864 | F7: =F5*Hypotheses!$B$32 -> 13.06368 | G7: =G5*Hypotheses!$B$32 -> 15.676416 | H7: =H5*Hypotheses!$B$32 -> 18.811699 | I7: =I5*Hypotheses!$B$32 -> 22.574039 | ... M7: =M5*Hypotheses!$B$32 -> 46.809527 | N7: =SUM(B7:M7) -> 249.35716
A8: Abonnés actifs (après churn) | B8: =B7 -> 6.3 | C8: =B8*(1-Hypotheses!$B$33)+C7 -> 13.23 | D8: =C8*(1-Hypotheses!$B$33)+D7 -> 20.979 | E8: =D8*(1-Hypotheses!$B$33)+E7 -> 29.7675 | F8: =E8*(1-Hypotheses!$B$33)+F7 -> 39.85443 | G8: =F8*(1-Hypotheses!$B$33)+G7 -> 51.545403 | H8: =G8*(1-Hypotheses!$B$33)+H7 -> 65.202562 | I8: =H8*(1-Hypotheses!$B$33)+I7 -> 81.256345 | J8: =I8*(1-Hypotheses!$B$33)+J7 -> 100.21956 | ... M8: =L8*(1-Hypotheses!$B$33)+M7 -> 181.30709
A10: Chiffre d'affaires encaissé | B10: =B8*Hypotheses!$B$9 -> 38.997 | C10: =C8*Hypotheses!$B$9 -> 81.8937 | D10: =D8*Hypotheses!$B$9 -> 129.86001 | E10: =E8*Hypotheses!$B$9 -> 184.26083 | F10: =F8*Hypotheses!$B$9 -> 246.69892 | G10: =G8*Hypotheses!$B$9 -> 319.06604 | H10: =H8*Hypotheses!$B$9 -> 403.60386 | I10: =I8*Hypotheses!$B$9 -> 502.97677 | ... M10: =M8*Hypotheses!$B$9 -> 1122.2909 | N10: =SUM(B10:M10) -> 5334.5905
A11: Commission Stripe | B11: =-(B10*Hypotheses!$B$23+B8*Hypotheses!$B$24) -> -2.159955 | C11: =-(C10*Hypotheses!$B$23+C8*Hypotheses!$B$24) -> -4.5359055 | D11: =-(D10*Hypotheses!$B$23+D8*Hypotheses!$B$24) -> -7.1926502 | E11: =-(E10*Hypotheses!$B$23+E8*Hypotheses!$B$24) -> -10.205787 | F11: =-(F10*Hypotheses!$B$23+F8*Hypotheses!$B$24) -> -13.664091 | G11: =-(G10*Hypotheses!$B$23+G8*Hypotheses!$B$24) -> -17.672341 | H11: =-(H10*Hypotheses!$B$23+H8*Hypotheses!$B$24) -> -22.354698 | I11: =-(I10*Hypotheses!$B$23+I8*Hypotheses!$B$24) -> -27.858738 | ... M11: =-(M10*Hypotheses!$B$23+M8*Hypotheses!$B$24) -> -62.161136 | N11: =SUM(B11:M11) -> -295.47082
A12: Cotisations et versement libératoire | B12: =-B10*Hypotheses!$B$16 -> -8.96931 | C12: =-C10*Hypotheses!$B$16 -> -18.835551 | D12: =-D10*Hypotheses!$B$16 -> -29.867802 | E12: =-E10*Hypotheses!$B$16 -> -42.37999 | F12: =-F10*Hypotheses!$B$16 -> -56.740752 | G12: =-G10*Hypotheses!$B$16 -> -73.38519 | H12: =-H10*Hypotheses!$B$16 -> -92.828887 | I12: =-I10*Hypotheses!$B$16 -> -115.68466 | ... M12: =-M10*Hypotheses!$B$16 -> -258.1269 | N12: =SUM(B12:M12) -> -1226.9558
A13: Coût IA des abonnés | B13: =-B8*(Hypotheses!$B$7*Couts!$C$28+Hypotheses!$B$8*Couts!$C$29) -> -24.203539 | C13: =-C8*(Hypotheses!$B$7*Couts!$C$28+Hypotheses!$B$8*Couts!$C$29) -> -50.827433 | D13: =-D8*(Hypotheses!$B$7*Couts!$C$28+Hypotheses!$B$8*Couts!$C$29) -> -80.597786 | E13: =-E8*(Hypotheses!$B$7*Couts!$C$28+Hypotheses!$B$8*Couts!$C$29) -> -114.36172 | F13: =-F8*(Hypotheses!$B$7*Couts!$C$28+Hypotheses!$B$8*Couts!$C$29) -> -153.11401 | G13: =-G8*(Hypotheses!$B$7*Couts!$C$28+Hypotheses!$B$8*Couts!$C$29) -> -198.02876 | H13: =-H8*(Hypotheses!$B$7*Couts!$C$28+Hypotheses!$B$8*Couts!$C$29) -> -250.49727 | I13: =-I8*(Hypotheses!$B$7*Couts!$C$28+Hypotheses!$B$8*Couts!$C$29) -> -312.1732 | ... M13: =-M8*(Hypotheses!$B$7*Couts!$C$28+Hypotheses!$B$8*Couts!$C$29) -> -696.55131 | N13: =SUM(B13:M13) -> -3310.9206
A14: Coût IA des utilisateurs gratuits | B14: =-B6*Couts!$C$27 -> -69.567208 | C14: =-C6*Couts!$C$27 -> -153.04786 | D14: =-D6*Couts!$C$27 -> -253.22464 | E14: =-E6*Couts!$C$27 -> -373.43677 | F14: =-F6*Couts!$C$27 -> -517.69134 | G14: =-G6*Couts!$C$27 -> -690.79681 | H14: =-H6*Couts!$C$27 -> -898.52338 | I14: =-I6*Couts!$C$27 -> -1147.7953 | ... M14: =-M6*Couts!$C$27 -> -2753.505 | N14: =SUM(B14:M14) -> -12346.998
A15: Total des coûts variables | B15: =SUM(B11:B14) -> -104.90001 | C15: =SUM(C11:C14) -> -227.24675 | D15: =SUM(D11:D14) -> -370.88288 | E15: =SUM(E11:E14) -> -540.38427 | F15: =SUM(F11:F14) -> -741.21019 | G15: =SUM(G11:G14) -> -979.8831 | H15: =SUM(H11:H14) -> -1264.2042 | I15: =SUM(I11:I14) -> -1603.5119 | ... M15: =SUM(M11:M14) -> -3770.3444 | N15: =SUM(B15:M15) -> -17180.345
A16: Marge sur coût variable | B16: =B10+B15 -> -65.903013 | C16: =C10+C15 -> -145.35305 | D16: =D10+D15 -> -241.02287 | E16: =E10+E15 -> -356.12345 | F16: =F10+F15 -> -494.51127 | G16: =G10+G15 -> -660.81706 | H16: =H10+H15 -> -860.60038 | I16: =I10+I15 -> -1100.5351 | ... M16: =M10+M15 -> -2648.0535 | N16: =SUM(B16:M16) -> -11845.754
A18: Charges fixes | B18: =-Hypotheses!$B$44 -> -47.5 | C18: =-Hypotheses!$B$44 -> -47.5 | D18: =-Hypotheses!$B$44 -> -47.5 | E18: =-Hypotheses!$B$44 -> -47.5 | F18: =-Hypotheses!$B$44 -> -47.5 | G18: =-Hypotheses!$B$44 -> -47.5 | H18: =-Hypotheses!$B$44 -> -47.5 | I18: =-Hypotheses!$B$44 -> -47.5 | ... M18: =-Hypotheses!$B$44 -> -47.5 | N18: =SUM(B18:M18) -> -570
A19: RÉSULTAT DU MOIS | B19: =B16+B18 -> -113.40301 | C19: =C16+C18 -> -192.85305 | D19: =D16+D18 -> -288.52287 | E19: =E16+E18 -> -403.62345 | F19: =F16+F18 -> -542.01127 | G19: =G16+G18 -> -708.31706 | H19: =H16+H18 -> -908.10038 | I19: =I16+I18 -> -1148.0351 | ... M19: =M16+M18 -> -2695.5535 | N19: =SUM(B19:M19) -> -12415.754
A20: Résultat cumulé | B20: =B19 -> -113.40301 | C20: =B20+C19 -> -306.25606 | D20: =C20+D19 -> -594.77893 | E20: =D20+E19 -> -998.40238 | F20: =E20+F19 -> -1540.4136 | G20: =F20+G19 -> -2248.7307 | H20: =G20+H19 -> -3156.8311 | I20: =H20+I19 -> -4304.8662 | J20: =I20+J19 -> -5740.9982 | ... M20: =L20+M19 -> -12415.754 | N20: =M20 -> -12415.754
A22: Contrôle des seuils
A23: CA annuel encaissé | B23: =N10 -> 5334.5905
A24: Sous le seuil de franchise de TVA ? | B24: =IF(N10<Hypotheses!B18,"Oui, pas de TVA à facturer","NON : TVA à facturer, revoir les prix TTC") -> Oui, pas de TVA à facturer
A25: Sous le plafond du régime micro ? | B25: =IF(N10<Hypotheses!B20,"Oui, régime micro conservé","NON : sortie du régime micro") -> Oui, régime micro conservé

Sheet Scenarios
A1: Trois scénarios
A2: Colonne B = configuration actuelle, reprise du modèle. Colonnes C et D = à toi de jouer avec les leviers.
B4: Actuel | C4: Optimisé | D4: Agressif
B5: Freemium généreux tel quel | C5: Gratuit bridé + essai payant | D5: Essai 7 jours + prix relevés
A6: LEVIERS
A7: Prix Pro (€/mois) | B7: =Hypotheses!B5 -> 4.99 | C7: 4.99 | D7: 6.99
A8: Prix Max (€/mois) | B8: =Hypotheses!B6 -> 8.99 | C8: 8.99 | D8: 11.99
A9: Part des abonnés en Pro | B9: =Hypotheses!B7 -> 0.7 | C9: 0.7 | D9: 0.7
A10: Taux de conversion vers payant | B10: =Hypotheses!B32 -> 0.021 | C10: 0.107 | D10: 0.107
A11: Coût IA mensuel d'un gratuit (€) | B11: =Couts!C27 -> 0.23686486 | C11: 0.06 | D11: 0.03
A12: Coût IA mensuel d'un abonné (€) | B12: =Hypotheses!B7*Couts!C28+Hypotheses!B8*Couts!C29 -> 3.8418316 | C12: 2.5 | D12: 2.5
A13: Churn mensuel | B13: =Hypotheses!B33 -> 0.1 | C13: 0.1 | D13: 0.1
A14: Charges fixes (€/mois) | B14: =Hypotheses!B44 -> 47.5 | C14: 47.5 | D14: 47.5
A16: RÉSULTAT PAR ABONNÉ
A17: ARPU (€) | B17: =B7*B9+B8*(1-B9) -> 6.19 | C17: =C7*C9+C8*(1-C9) -> 6.19 | D17: =D7*D9+D8*(1-D9) -> 8.49
A18: Commission Stripe (€) | B18: =-(B17*Hypotheses!$B$23+Hypotheses!$B$24) -> -0.34285 | C18: =-(C17*Hypotheses!$B$23+Hypotheses!$B$24) -> -0.34285 | D18: =-(D17*Hypotheses!$B$23+Hypotheses!$B$24) -> -0.37735
A19: Cotisations + IR (€) | B19: =-B17*Hypotheses!$B$16 -> -1.4237 | C19: =-C17*Hypotheses!$B$16 -> -1.4237 | D19: =-D17*Hypotheses!$B$16 -> -1.9527
A20: Coût IA de l'abonné (€) | B20: =-B12 -> -3.8418316 | C20: =-C12 -> -2.5 | D20: =-D12 -> -2.5
A21: Gratuits portés par abonné | B21: =IF(B10<=0,0,1/B10-1) -> 46.619048 | C21: =IF(C10<=0,0,1/C10-1) -> 8.3457944 | D21: =IF(D10<=0,0,1/D10-1) -> 8.3457944
A22: Coût IA des gratuits portés (€) | B22: =-B21*B11 -> -11.042414 | C22: =-C21*C11 -> -0.50074766 | D22: =-D21*D11 -> -0.25037383
A23: MARGE SUR COÛT VARIABLE (€) | B23: =B17+B18+B19+B20+B22 -> -10.460796 | C23: =C17+C18+C19+C20+C22 -> 1.4227023 | D23: =D17+D18+D19+D20+D22 -> 3.4095762
A25: VERDICT
A26: Seuil de rentabilité (abonnés) | B26: =IF(B23<=0,"Jamais atteint",B14/B23) -> Jamais atteint | C26: =IF(C23<=0,"Jamais atteint",C14/C23) -> 33.387167 | D26: =IF(D23<=0,"Jamais atteint",D14/D23) -> 13.93135
A27: Inscrits gratuits nécessaires | B27: =IF(B23<=0,"Jamais atteint",B26/B10) -> Jamais atteint | C27: =IF(C23<=0,"Jamais atteint",C26/C10) -> 312.02959 | D27: =IF(D23<=0,"Jamais atteint",D26/D10) -> 130.19954
A28: CA mensuel au seuil (€) | B28: =IF(B23<=0,"Jamais atteint",B26*B17) -> Jamais atteint | C28: =IF(C23<=0,"Jamais atteint",C26*C17) -> 206.66656 | D28: =IF(D23<=0,"Jamais atteint",D26*D17) -> 118.27716
A29: Valeur vie d'un abonné (€) | B29: =IF(B13<=0,0,B23/B13) -> -104.60796 | C29: =IF(C13<=0,0,C23/C13) -> 14.227023 | D29: =IF(D13<=0,0,D23/D13) -> 34.095762
A31: Résultat mensuel à 100 abonnés (€) | B31: =100*B23-B14 -> -1093.5796 | C31: =100*C23-C14 -> 94.770234 | D31: =100*D23-D14 -> 293.45762
A32: Résultat mensuel à 300 abonnés (€) | B32: =300*B23-B14 -> -3185.7387 | C32: =300*C23-C14 -> 379.3107 | D32: =300*D23-D14 -> 975.37285
A33: Résultat mensuel à 1 000 abonnés (€) | B33: =1000*B23-B14 -> -10508.296 | C33: =1000*C23-C14 -> 1375.2023 | D33: =1000*D23-D14 -> 3362.0762
A35: CE QUI CHANGE ENTRE LES SCÉNARIOS
A36: Optimisé : le quota gratuit est divisé par environ quatre, et le gratuit permanent devient un essai qui pousse à payer.
A37: La conversion passe de 2,1 % à 10,7 %, écart médian mesuré entre freemium et paywall dur (RevenueCat 2026).
A38: Le coût IA par abonné baisse à 2,50 € en raccourcissant les sorties du modèle et en limitant l'OCR.
A39: Agressif : mêmes leviers, plus une hausse de prix à 6,99 € et 11,99 €, cohérente avec un produit qui délivre vraiment.
A41: Le levier décisif n'est pas le prix. C'est le nombre de gratuits que chaque abonné doit financer.
A42: À 2,1 % de conversion, un abonné en porte 47. À 10,7 %, il n'en porte plus que 8.
